nnbma/__init__.py
nnbma/dataset/__init__.py
nnbma/dataset/mask_dataset.py
nnbma/dataset/regression_dataset.py
nnbma/layers/__init__.py
nnbma/layers/additional_module.py
nnbma/layers/polynomial_expansion.py
nnbma/layers/restrictable_linear.py
nnbma/learning/__init__.py
nnbma/learning/batch_scheduler.py
nnbma/learning/loss_functions.py
nnbma/learning/network_learning.py
nnbma/learning/regression_metrics.py
nnbma/networks/__init__.py
nnbma/networks/densely_connected.py
nnbma/networks/embedding_network.py
nnbma/networks/fully_connected.py
nnbma/networks/merging_network.py
nnbma/networks/neural_network.py
nnbma/networks/polynomial_network.py
nnbma/operators/__init__.py
nnbma/operators/base.py
nnbma/operators/normalization.py
nnbma/operators/operator.py
nnbma-1.0.2.dist-info/LICENSE
nnbma-1.0.2.dist-info/METADATA
nnbma-1.0.2.dist-info/WHEEL
nnbma-1.0.2.dist-info/RECORD
