Metadata-Version: 2.1
Name: nnbma
Version: 1.0.2
Summary: Neural network-based model approximation (nnbma)
Home-page: https://github.com/einigl/ism-model-nn-approximation
Keywords: machine learning,neural network
Author: Lucas Einig
Requires-Python: >=3.8
Classifier: License :: OSI Approved :: MIT License
Classifier: Operating System :: OS Independent
Classifier: Programming Language :: Python :: 3
Classifier: Programming Language :: Python :: 3.8
Classifier: Programming Language :: Python :: 3.9
Classifier: Programming Language :: Python :: 3.10
Classifier: Programming Language :: Python :: 3.11
Classifier: Programming Language :: Python :: 3.12
Requires-Dist: jupyter (>=1.0.0,<2.0.0)
Requires-Dist: matplotlib (>=3.6.2,<4.0.0)
Requires-Dist: more-itertools (>=10.0.0,<11.0.0)
Requires-Dist: numpy (>=1.20.2,<2.0.0)
Requires-Dist: pandas (>=1.3.4)
Requires-Dist: torch (>=2.0.0,!=2.0.1,!=2.1.0)
Requires-Dist: tqdm (>=4.62.3,<5.0.0)
Project-URL: Bug Tracker, https://github.com/einigl/ism-model-nn-approximation/issues
Project-URL: Documentation, https://ism-model-nn-approximation.readthedocs.io/en/latest/
Project-URL: Repository, https://github.com/einigl/ism-model-nn-approximation
